altmo/__init__.py
altmo/api/__init__.py
altmo/api/valhalla.py
altmo/batches.py
altmo/commands/__init__.py
altmo/commands/build.py
altmo/commands/create_study_area.py
altmo/commands/export.py
altmo/commands/network_distances.py
altmo/commands/raster.py
altmo/commands/schema.py
altmo/commands/straight_distances.py
altmo/data/__init__.py
altmo/data/decorators.py
altmo/data/read.py
altmo/data/result_sets.py
altmo/data/schema.py
altmo/data/types.py
altmo/data/utils.py
altmo/data/write.py
altmo/errors.py
altmo/main.py
altmo/settings.py
altmo/utils.py
altmo/validators.py
altmo-0.1.2.dist-info/entry_points.txt
altmo-0.1.2.dist-info/LICENSE
altmo-0.1.2.dist-info/WHEEL
altmo-0.1.2.dist-info/METADATA
altmo-0.1.2.dist-info/RECORD
