Metadata-Version: 2.1
Name: altmo
Version: 0.1.2
Summary: Tools for mapping walkability and bikeability using Open Street Map data
Home-page: https://altmo.readthedocs.io
License: GPLv3
Keywords: OpenStreetMap,GIS
Author: Travis Hathaway
Author-email: travis.j.hathaway@gmail.com
Requires-Python: >=3.9,<4.0
Classifier: License :: Other/Proprietary License
Classifier: Programming Language :: Python :: 3
Classifier: Programming Language :: Python :: 3.9
Provides-Extra: raster
Requires-Dist: PyYAML (>=6.0,<7.0)
Requires-Dist: aiocsv (>=1.2.1,<2.0.0)
Requires-Dist: aiofiles (>=0.8.0,<0.9.0)
Requires-Dist: aiohttp (>=3.8.1,<4.0.0)
Requires-Dist: aiopg (>=1.3.3,<2.0.0)
Requires-Dist: click (>=8.0.1,<9.0.0)
Requires-Dist: psycopg2 (>=2.8.6,<3.0.0)
Requires-Dist: pygdal (==3.2.1.10); extra == "raster"
Requires-Dist: requests (>=2.25.1,<3.0.0)
Requires-Dist: tqdm (>=4.61.0,<5.0.0)
Project-URL: Documentation, https://altmo.readthedocs.io
Project-URL: Repository, https://github.com/travishathaway/altmo
